pybda/__init__.py
pybda/clustering.py
pybda/decorators.py
pybda/dimension_reduction.py
pybda/ensemble.py
pybda/factor_analysis.py
pybda/forest.py
pybda/gbm.py
pybda/glm.py
pybda/globals.py
pybda/gmm.py
pybda/ica.py
pybda/kmeans.py
pybda/kpca.py
pybda/lda.py
pybda/logger.py
pybda/outliers.py
pybda/pca.py
pybda/pybda.snake
pybda/pybda_config.py
pybda/regression.py
pybda/sampler.py
pybda/spark_model.py
pybda/spark_session.py
pybda/config/__init__.py
pybda/config/config_checks.py
pybda/config/rule_node.py
pybda/config/rule_tree.py
pybda/fit/__init__.py
pybda/fit/clustering_fit.py
pybda/fit/clustering_fit_profile.py
pybda/fit/clustering_transformed.py
pybda/fit/dimension_reduction_fit.py
pybda/fit/dimension_reduction_transform.py
pybda/fit/ensemble_fit.py
pybda/fit/factor_analysis_fit.py
pybda/fit/factor_analysis_transform.py
pybda/fit/gbm_fit.py
pybda/fit/glm_fit.py
pybda/fit/gmm_fit.py
pybda/fit/gmm_fit_profile.py
pybda/fit/gmm_transformed.py
pybda/fit/ica_fit.py
pybda/fit/ica_transform.py
pybda/fit/kmeans_fit.py
pybda/fit/kmeans_fit_profile.py
pybda/fit/kmeans_transformed.py
pybda/fit/kpca_fit.py
pybda/fit/kpca_transform.py
pybda/fit/lda_fit.py
pybda/fit/lda_transform.py
pybda/fit/pca_fit.py
pybda/fit/pca_transform.py
pybda/fit/predicted_data.py
pybda/fit/regression_fit.py
pybda/fit/transformed_data.py
pybda/io/__init__.py
pybda/io/as_filename.py
pybda/io/file.py
pybda/io/io.py
pybda/plot/__init__.py
pybda/plot/descriptive.py
pybda/plot/dimension_reduction_plot.py
pybda/plot/regression_plot.py
pybda/spark/__init__.py
pybda/spark/dataframe.py
pybda/spark/features.py
pybda/stats/__init__.py
pybda/stats/linalg.py
pybda/stats/random.py
pybda/stats/stats.py
pybda/util/__init__.py
pybda/util/cast_as.py
pybda/util/string.py
pybda-0.1.0.data/scripts/pybda
tests/__init__.py
tests/test_api.py
tests/test_clustering_api.py
tests/test_dimred_api.py
tests/test_fa.py
tests/test_forest.py
tests/test_gbm.py
tests/test_glm.py
tests/test_gmm.py
tests/test_ica.py
tests/test_kmeans.py
pybda-0.1.0.dist-info/LICENSE
pybda-0.1.0.dist-info/METADATA
pybda-0.1.0.dist-info/WHEEL
pybda-0.1.0.dist-info/top_level.txt
pybda-0.1.0.dist-info/RECORD
