Metadata-Version: 2.1
Name: pybda
Version: 0.1.0
Summary: Analysis of big biological data sets for distributed HPC clusters.
Home-page: https://github.com/cbg-ethz/pybda
Author: Simon Dirmeier
Author-email: simon.dirmeier@web.de
License: GPLv3
Keywords: bigdata analysis pipeline workflow spark pyspark machinelearning
Platform: UNKNOWN
Classifier: Development Status :: 3 - Alpha
Classifier: Environment :: Console
Classifier: Intended Audience :: End Users/Desktop
Classifier: License :: OSI Approved :: GNU General Public License v3 (GPLv3)
Classifier: Programming Language :: Python :: 3
Classifier: Programming Language :: Python :: 3.4
Classifier: Programming Language :: Python :: 3.5
Classifier: Programming Language :: Python :: 3.6
Requires-Python: >=3
Requires-Dist: click (>=6.7)
Requires-Dist: joypy (>=0.1.9)
Requires-Dist: matplotlib (>=2.2.3)
Requires-Dist: numpy (>=1.15.0)
Requires-Dist: pandas (>=0.23.3)
Requires-Dist: pyspark (==2.4.0)
Requires-Dist: scipy (>=1.0.0)
Requires-Dist: seaborn (>=0.9.0)
Requires-Dist: snakemake (>=5.2.2)
Requires-Dist: sparkhpc (>=0.3.post4)
Provides-Extra: dev
Requires-Dist: coverage ; extra == 'dev'
Requires-Dist: findspark ; extra == 'dev'
Requires-Dist: flake8 ; extra == 'dev'
Requires-Dist: pylint ; extra == 'dev'
Requires-Dist: pytest (>=3.6.2) ; extra == 'dev'
Requires-Dist: pytest-cov ; extra == 'dev'
Requires-Dist: pytest-pep8 ; extra == 'dev'
Requires-Dist: scikit-learn ; extra == 'dev'
Requires-Dist: yapf ; extra == 'dev'
Requires-Dist: sphinx ; extra == 'dev'
Requires-Dist: sphinx-fontawesome ; extra == 'dev'
Requires-Dist: sphinxcontrib-fulltoc ; extra == 'dev'
Provides-Extra: doc
Requires-Dist: sphinx ; extra == 'doc'
Requires-Dist: sphinx-fontawesome ; extra == 'doc'
Requires-Dist: sphinxcontrib-fulltoc ; extra == 'doc'
Provides-Extra: test
Requires-Dist: coverage ; extra == 'test'
Requires-Dist: findspark ; extra == 'test'
Requires-Dist: flake8 ; extra == 'test'
Requires-Dist: pylint ; extra == 'test'
Requires-Dist: pytest (>=3.6.2) ; extra == 'test'
Requires-Dist: pytest-cov ; extra == 'test'
Requires-Dist: pytest-pep8 ; extra == 'test'
Requires-Dist: scikit-learn ; extra == 'test'
Requires-Dist: yapf ; extra == 'test'
